LICENSE
README.md
setup.cfg
setup.py
sentry_dingtalkv/__init__.py
sentry_dingtalkv/plugin.py
sentry_dingtalkv.egg-info/PKG-INFO
sentry_dingtalkv.egg-info/SOURCES.txt
sentry_dingtalkv.egg-info/dependency_links.txt
sentry_dingtalkv.egg-info/entry_points.txt
sentry_dingtalkv.egg-info/requires.txt
sentry_dingtalkv.egg-info/top_level.txt