Metadata-Version: 2.1
Name: sentry-dingtalkv
Version: 1.0.2
Summary: A sentry extension integrates dingtalkv robot webhook
Home-page: https://gitlab.xiaoman.cc/sourceliu/sentry-dingtalkv
Author: source
Author-email: source@qq.com
License: MIT
Keywords: sentry dingtalkv
Platform: UNKNOWN
Classifier: License :: OSI Approved :: MIT License
Classifier: Programming Language :: Python
Classifier: Programming Language :: Python :: 3
Classifier: Programming Language :: Python :: 3.6
Classifier: Programming Language :: Python :: 3.7
Classifier: Programming Language :: Python :: Implementation :: CPython
Requires-Python: >=3.6.13
License-File: LICENSE
